setup.py
distributions_stats/Binomialdistribution.py
distributions_stats/Gaussiandistribution.py
distributions_stats/Generaldistribution.py
distributions_stats/__init__.py
distributions_stats.egg-info/PKG-INFO
distributions_stats.egg-info/SOURCES.txt
distributions_stats.egg-info/dependency_links.txt
distributions_stats.egg-info/not-zip-safe
distributions_stats.egg-info/top_level.txt