Metadata-Version: 1.0
Name: distributions-stats
Version: 0.1
Summary: Basic statistical distributions
Home-page: UNKNOWN
Author: Mateus Cichelero
Author-email: eng.cichelero@gmail.com
License: UNKNOWN
Platform: UNKNOWN
